deeponto/__init__.py
deeponto/align/__init__.py
deeponto/align/evaluation.py
deeponto/align/mapping.py
deeponto/align/oaei.py
deeponto/align/bertmap/__init__.py
deeponto/align/bertmap/bert_classifier.py
deeponto/align/bertmap/default_config.yaml
deeponto/align/bertmap/mapping_prediction.py
deeponto/align/bertmap/mapping_refinement.py
deeponto/align/bertmap/pipeline.py
deeponto/align/bertmap/text_semantics.py
deeponto/align/bertsubs/__init__.py
deeponto/align/logmap/__init__.py
deeponto/align/logmap/logmap-matcher-4.0.jar
deeponto/align/logmap/java-dependencies/__init__.py
deeponto/align/logmap/java-dependencies/aopalliance-1.0.jar
deeponto/align/logmap/java-dependencies/apache-mime4j-core-0.7.2.jar
deeponto/align/logmap/java-dependencies/automaton-1.11-8.jar
deeponto/align/logmap/java-dependencies/avalon-framework-4.1.3.jar
deeponto/align/logmap/java-dependencies/axiom-api-1.2.14.jar
deeponto/align/logmap/java-dependencies/axiom-c14n-1.2.14.jar
deeponto/align/logmap/java-dependencies/axiom-dom-1.2.14.jar
deeponto/align/logmap/java-dependencies/axiom-impl-1.2.14.jar
deeponto/align/logmap/java-dependencies/commons-beanutils-1.9.3.jar
deeponto/align/logmap/java-dependencies/commons-codec-1.6.jar
deeponto/align/logmap/java-dependencies/commons-collections-3.2.2.jar
deeponto/align/logmap/java-dependencies/commons-io-2.6.jar
deeponto/align/logmap/java-dependencies/commons-io-2.7.jar
deeponto/align/logmap/java-dependencies/commons-lang-2.4.jar
deeponto/align/logmap/java-dependencies/commons-lang3-3.5.jar
deeponto/align/logmap/java-dependencies/commons-logging-1.1.jar
deeponto/align/logmap/java-dependencies/dom4j-1.6.1.jar
deeponto/align/logmap/java-dependencies/dom4j-2.1.3.jar
deeponto/align/logmap/java-dependencies/elk-owl-implementation-0.4.3.jar
deeponto/align/logmap/java-dependencies/elk-owl-model-0.4.3.jar
deeponto/align/logmap/java-dependencies/elk-owlapi-0.4.3.jar
deeponto/align/logmap/java-dependencies/elk-reasoner-0.4.3.jar
deeponto-0.9.3.dist-info/LICENSE
deeponto-0.9.3.dist-info/METADATA
deeponto-0.9.3.dist-info/WHEEL
deeponto-0.9.3.dist-info/top_level.txt
deeponto-0.9.3.dist-info/RECORD
