Metadata-Version: 2.2
Name: deeponto
Version: 0.9.3
Summary: DeepOnto aims to provide implemented deep learning models and an evaluation platform for various ontology engineering purposes.
Author-email: Yuan He <yuan.he@cs.ox.ac.uk>, Jiaoyan Chen <jiaoyan.chen@manchester.ac.uk>
Maintainer-email: Yuan He <yuan.he@cs.ox.ac.uk>
License: Apache License 2.0
Project-URL: Homepage, https://krr-oxford.github.io/DeepOnto/
Project-URL: Repository, https://github.com/KRR-Oxford/DeepOnto
Classifier: Programming Language :: Python :: 3.8
Classifier: Programming Language :: Python :: 3.9
Classifier: Programming Language :: Python :: 3.10
Classifier: License :: OSI Approved :: Apache Software License
Classifier: Intended Audience :: Developers
Classifier: Intended Audience :: Science/Research
Requires-Python: >=3.8
License-File: LICENSE
Requires-Dist: JPype1
Requires-Dist: yacs
Requires-Dist: torch
Requires-Dist: anytree
Requires-Dist: click
Requires-Dist: dill
Requires-Dist: pandas
Requires-Dist: numpy
Requires-Dist: scikit_learn
Requires-Dist: transformers[torch]
Requires-Dist: datasets
Requires-Dist: spacy
Requires-Dist: pprintpp
Requires-Dist: networkx
Requires-Dist: lxml
Requires-Dist: textdistance
Requires-Dist: ipywidgets
Requires-Dist: ipykernel
Requires-Dist: enlighten
Requires-Dist: rdflib
Requires-Dist: nltk
Provides-Extra: docs
Requires-Dist: mkdocs>=1.4.2; extra == "docs"
Requires-Dist: mkdocstrings>=0.19.1; extra == "docs"
Requires-Dist: mkdocs-material>=9.0.5; extra == "docs"
Requires-Dist: mkdocs-include-markdown-plugin>=4.0.3; extra == "docs"
Requires-Dist: mkdocstrings-python>=0.8.3; extra == "docs"
Requires-Dist: mkdocs-git-revision-date-localized-plugin; extra == "docs"
Requires-Dist: mkdocs-git-authors-plugin; extra == "docs"
Provides-Extra: ontolama
Requires-Dist: openprompt; extra == "ontolama"
